pyagresso/__init__.py
pyagresso/queryengineservice.py
pyagresso-0.2.0.dev1.dist-info/METADATA
pyagresso-0.2.0.dev1.dist-info/RECORD
pyagresso-0.2.0.dev1.dist-info/WHEEL
pyagresso-0.2.0.dev1.dist-info/top_level.txt
