Metadata-Version: 2.1
Name: pyagresso
Version: 0.2.0.dev1
Summary: Python Client for Unit4 Agresso System
Home-page: https://github.com/osamakhn/pyagresso
Author: Osama Khan
Author-email: osamakhn@gmail.com
License: MIT License
Project-URL: Source, https://www.github.com/osamakhn/pyagresso
Keywords: Unit4 Agresso Milestone4
Platform: UNKNOWN
Requires-Dist: requests
